com/phida/main/Maintenance.py
com/phida/main/Operations.py
com/phida/main/PartitionAnalyzer.py
com/phida/main/PerfAnalyzer.py
com/phida/main/SilverMerge.py
com/phida/main/WorkflowBuilder.py
com/phida/main/__init__.py
com/phida/main/logging.py
com/phida/main/sparksession.py
com/phida/main/utils.py
com/phida/main/utilsDatabricksAPI.py
com/phida/tests/OperationsTest.py
com/phida/tests/__init__.py
com/phida/tests/main_test.py
com/phida/tests/utils_test.py
silverstreamingapplication-1.5.dist-info/METADATA
silverstreamingapplication-1.5.dist-info/WHEEL
silverstreamingapplication-1.5.dist-info/top_level.txt
silverstreamingapplication-1.5.dist-info/RECORD
