Metadata-Version: 2.1
Name: silverstreamingapplication
Version: 1.5
Summary: initial version
Home-page: 
Author: 
Author-email: 
